__init__.py
cc_pyspark/__init__.py
cc_pyspark/bs4_parser.py
cc_pyspark/iana_tld.py
cc_pyspark/json_importer.py
cc_pyspark/resiliparse_parser.py
cc_pyspark/sparkcc.py
cc_pyspark/sparkcc_fastwarc.py
cc_pyspark/jobs/__init__.py
cc_pyspark/jobs/cc_index_export.py
cc_pyspark/jobs/cc_index_word_count.py
cc_pyspark/jobs/hostlinks_extract_fastwarc.py
cc_pyspark/jobs/hostlinks_to_graph.py
cc_pyspark/jobs/html_tag_count.py
cc_pyspark/jobs/linkmap2parquet.py
cc_pyspark/jobs/server_count.py
cc_pyspark/jobs/server_count_fastwarc.py
cc_pyspark/jobs/server_ip_address.py
cc_pyspark/jobs/sitemaps_from_robotstxt.py
cc_pyspark/jobs/sitemaps_from_robotstxt_fastwarc.py
cc_pyspark/jobs/wat_extract_links.py
cc_pyspark/jobs/word_count.py
cc_pyspark-0.1.0.dev0.dist-info/licenses/LICENSE
cc_pyspark-0.1.0.dev0.dist-info/METADATA
cc_pyspark-0.1.0.dev0.dist-info/WHEEL
cc_pyspark-0.1.0.dev0.dist-info/top_level.txt
cc_pyspark-0.1.0.dev0.dist-info/RECORD
