Metadata-Version: 2.4
Name: cc-pyspark
Version: 0.1.0.dev0
Summary: Common Crawl data processing examples for PySpark.
License: MIT
Requires-Python: >=3.9
License-File: LICENSE
Requires-Dist: beautifulsoup4>=4.14.2
Requires-Dist: boto3>=1.40.63
Requires-Dist: botocore>=1.40.63
Requires-Dist: idna>=3.11
Requires-Dist: lxml>=6.0.2
Requires-Dist: orjson>=3.11.4
Requires-Dist: pytest>=8.4.2
Requires-Dist: pytest-mock>=3.15.1
Requires-Dist: requests>=2.32.5
Requires-Dist: ujson>=5.11.0
Requires-Dist: warcio>=1.7.5
Dynamic: license-file
